syntab
