Metadata-Version: 1.1
Name: syntab
Version: 0.1.4
Summary: syn table schema from db1 to db2
Home-page: https://pypi.python.org/pypi/syntab
Author: Andrew liu
Author-email: 1185978974@qq.com
License: GPL
Keywords: syn table python python3
Platform: UNKNOWN
Classifier: License :: OSI Approved :: MIT License
Classifier: Programming Language :: Python
Classifier: Intended Audience :: Developers
Classifier: Operating System :: OS Independent
